llm_chatbot/__init__.py
llm_chatbot/__main__.py
llm_chatbot/cli.py
llm_chatbot/commands.py
llm_chatbot/config.py
llm_chatbot/costs.py
llm_chatbot/discord_bot.py
llm_chatbot/i18n.py
llm_chatbot/listener.py
llm_chatbot/memory.py
llm_chatbot/openai_client.py
llm_chatbot/personality.py
llm_chatbot/runtime_utils.py
llm_chatbot/streaming.py
llm_chatbot/locales/en.yml
llm_chatbot/locales/fr.yml
llm_chatbot_kit-0.1.0.dist-info/METADATA
llm_chatbot_kit-0.1.0.dist-info/WHEEL
llm_chatbot_kit-0.1.0.dist-info/entry_points.txt
llm_chatbot_kit-0.1.0.dist-info/top_level.txt
llm_chatbot_kit-0.1.0.dist-info/RECORD
