Metadata-Version: 2.4
Name: llm-chatbot-kit
Version: 0.1.0
Summary: Developer-first kit for LLM chatbots with streaming, memory, and personas (Discord-first)
Author-email: Maiko BOSSUYT <hello@maiko-bossuyt.eu>
Requires-Python: >=3.9
Requires-Dist: discord.py>=2.3
Requires-Dist: openai>=1.40.0
Requires-Dist: PyYAML>=6.0
Requires-Dist: coloredlogs>=15.0
